{
  "space_id": "52Hz/SRMNet_real_world_denoising",
  "title": "SRMNet_real_denoising",
  "emoji": "\ud83c\udf2a",
  "description": "SRMNet_real_denoising",
  "input_schema": {
    "input": {
      "type": "string",
      "description": "Input",
      "required": true
    }
  },
  "output_schema": {
    "output": {
      "type": "string"
    }
  },
  "license": "unknown",
  "hardware": "",
  "sdk": "gradio",
  "tags": [
    "gradio",
    "region:us"
  ],
  "likes": 18,
  "last_modified": "2023-05-31 10:03:04+00:00",
  "readme_excerpt": "",
  "_real_scraped": true,
  "_api_scraped": true,
  "_api_status": "sleeping",
  "_api_error": "Space is in RUNTIME_ERROR state",
  "estimated_latency_s": 10.0,
  "speed_tier": "medium",
  "_latency_source": "inferred"
}