{
  "space_id": "bigcode/bigcode-models-leaderboard",
  "title": "Big Code Models Leaderboard",
  "emoji": "\ud83d\udcc8",
  "description": "Big Code Models Leaderboard",
  "input_schema": {
    "input": {
      "type": "string",
      "description": "Input",
      "required": true
    }
  },
  "output_schema": {
    "output": {
      "type": "string"
    }
  },
  "license": "unknown",
  "hardware": "4.36.1",
  "sdk": "gradio",
  "tags": [
    "gradio",
    "leaderboard",
    "eval:code",
    "test:public",
    "judge:auto",
    "submission:semiautomatic",
    "region:us",
    "benchmark",
    "code",
    "code-generation"
  ],
  "likes": 1502,
  "last_modified": "2024-11-11 20:36:38+00:00",
  "readme_excerpt": "",
  "_real_scraped": true,
  "_api_scraped": true,
  "_api_status": "error",
  "_api_error": "Server error '500 Internal Server Error' for url 'https://huggingface.co/api/spaces/bigcode/bigcode-models-leaderboard' (Request ID: Root=1-69e5b0f3-77faf30109e7989e63870ebf;db132133-39df-4c9c-bec5-61",
  "estimated_latency_s": 10.0,
  "speed_tier": "medium",
  "_latency_source": "inferred",
  "_tags_enriched": true
}