{
  "space_id": "bigscience-data/bigscience-corpus",
  "title": "Bigscience Corpus",
  "emoji": "\ud83c\udf0d",
  "description": "Bigscience Corpus",
  "input_schema": {
    "input": {
      "type": "string",
      "description": "Input",
      "required": true
    }
  },
  "output_schema": {
    "output": {
      "type": "string"
    }
  },
  "license": "apache-2.0",
  "hardware": "1.26.0",
  "sdk": "streamlit",
  "tags": [
    "streamlit",
    "region:us"
  ],
  "likes": 6,
  "last_modified": "2023-09-08 11:03:26+00:00",
  "readme_excerpt": "",
  "_real_scraped": true,
  "estimated_latency_s": 10.0,
  "speed_tier": "medium",
  "_latency_source": "inferred",
  "_api_scraped": true,
  "_api_status": "sleeping",
  "_api_error": "Space is in RUNTIME_ERROR state"
}