{
  "space_id": "course-demos/Remove-bg",
  "title": "Remove Bg",
  "emoji": "\ud83c\udf16",
  "description": "Remove Bg",
  "input_schema": {
    "input": {
      "type": "string",
      "description": "Input",
      "required": true
    }
  },
  "output_schema": {
    "output": {
      "type": "string"
    }
  },
  "license": "afl-3.0",
  "hardware": "5.45.0",
  "sdk": "gradio",
  "tags": [
    "gradio",
    "region:us"
  ],
  "likes": 2,
  "last_modified": "2025-09-12 13:53:37+00:00",
  "readme_excerpt": "",
  "_real_scraped": true,
  "estimated_latency_s": 10.0,
  "speed_tier": "medium",
  "_latency_source": "inferred",
  "_api_scraped": true,
  "_api_status": "sleeping",
  "_api_error": "Space is in RUNTIME_ERROR state"
}