{
  "space_id": "duchaba/120dog_breeds",
  "title": "Dog Breeds",
  "emoji": "\ud83c\udf0d",
  "description": "Dog Breeds",
  "input_schema": {
    "input": {
      "type": "string",
      "description": "Input",
      "required": true
    }
  },
  "output_schema": {
    "output": {
      "type": "string"
    }
  },
  "license": "mit",
  "hardware": "3.0.18",
  "sdk": "gradio",
  "tags": [
    "gradio",
    "region:us"
  ],
  "likes": 12,
  "last_modified": "2023-08-28 23:25:13+00:00",
  "readme_excerpt": "",
  "_real_scraped": true,
  "_api_scraped": true,
  "_api_status": "ok",
  "endpoints": [],
  "_api_verified": true,
  "estimated_latency_s": 2.62,
  "speed_tier": "fast",
  "_latency_source": "measured",
  "measured_latency_s": 2.62,
  "measurement_method": "gradio_client_init_plus_view_api",
  "measurement_timestamp": "2026-04-20T07:50:29.906008+00:00"
}