{
  "space_id": "elonmuskceo/persistent-data",
  "title": "Persistent Data",
  "emoji": "\ud83d\udc28",
  "description": "Persistent Data",
  "input_schema": {
    "input": {
      "type": "string",
      "description": "Input",
      "required": true
    }
  },
  "output_schema": {
    "output": {
      "type": "string"
    }
  },
  "license": "unknown",
  "hardware": "2.4.2",
  "sdk": "gradio",
  "tags": [
    "gradio",
    "region:us"
  ],
  "likes": 5,
  "last_modified": "2022-04-07 08:10:34+00:00",
  "readme_excerpt": "",
  "_real_scraped": true,
  "estimated_latency_s": 10.0,
  "speed_tier": "medium",
  "_latency_source": "inferred",
  "_api_scraped": true,
  "_api_status": "error",
  "_api_error": "(Request ID: Root=1-69e77b8f-1a04255a70e93f172fa2f6e0;2940cabb-1adb-44cd-9f09-6f71978ce4b6)\n\n429 Too Many Requests: you have reached your 'api' rate limit.\nRetry after 79 seconds (0/2500 requests rema"
}