{
  "space_id": "erc/entity-referring-classifier",
  "title": "Entity Referring Classifier",
  "emoji": "\ud83d\ude80",
  "description": "Entity Referring Classifier",
  "input_schema": {
    "input": {
      "type": "string",
      "description": "Input",
      "required": true
    }
  },
  "output_schema": {
    "output": {
      "type": "string"
    }
  },
  "license": "unknown",
  "hardware": "",
  "sdk": "streamlit",
  "tags": [
    "streamlit",
    "region:us"
  ],
  "likes": 3,
  "last_modified": "2021-12-17 08:01:12+00:00",
  "readme_excerpt": "",
  "_real_scraped": true,
  "estimated_latency_s": 10.0,
  "speed_tier": "medium",
  "_latency_source": "inferred",
  "_api_scraped": true,
  "_api_status": "error",
  "_api_error": "(Request ID: Root=1-69e77bd9-21e2bc5435be5a5d1701db14;37d6e6c4-f7f4-4e98-aa59-8f6d40d7e2a0)\n\n429 Too Many Requests: you have reached your 'api' rate limit.\nRetry after 5 seconds (0/2500 requests remai"
}