{
  "space_id": "Huertas97/Inpaint_Me",
  "title": "Inpaint_Me",
  "emoji": "\ud83c\udfa8",
  "description": "Inpaint_Me",
  "input_schema": {
    "input": {
      "type": "string",
      "description": "Input",
      "required": true
    }
  },
  "output_schema": {
    "output": {
      "type": "string"
    }
  },
  "license": "apache-2.0",
  "hardware": "",
  "sdk": "streamlit",
  "tags": [
    "streamlit",
    "region:us",
    "image-generation",
    "vision"
  ],
  "likes": 11,
  "last_modified": "2024-01-19 19:14:27+00:00",
  "readme_excerpt": "",
  "_real_scraped": true,
  "_api_scraped": true,
  "_api_status": "sleeping",
  "_api_error": "Space is in RUNTIME_ERROR state",
  "estimated_latency_s": 10.0,
  "speed_tier": "medium",
  "_latency_source": "inferred",
  "_tags_enriched": true
}