{
  "space_id": "huggan/butterfly-gan",
  "title": "Butterfly GAN",
  "emoji": "\ud83e\udd8b",
  "description": "Butterfly GAN",
  "input_schema": {
    "input": {
      "type": "string",
      "description": "Input",
      "required": true
    }
  },
  "output_schema": {
    "output": {
      "type": "string"
    }
  },
  "license": "apache-2.0",
  "hardware": "1.2.0",
  "sdk": "streamlit",
  "tags": [
    "streamlit",
    "region:us"
  ],
  "likes": 26,
  "last_modified": "2022-07-07 03:22:08+00:00",
  "readme_excerpt": "",
  "_real_scraped": true,
  "_api_scraped": true,
  "_api_status": "sleeping",
  "_api_error": "Space is in RUNTIME_ERROR state",
  "estimated_latency_s": 10.0,
  "speed_tier": "medium",
  "_latency_source": "inferred"
}