{
  "space_id": "jph00/minimal",
  "title": "Minimal",
  "emoji": "\ud83d\udc41",
  "description": "Minimal",
  "input_schema": {
    "input": {
      "type": "string",
      "description": "Input",
      "required": true
    }
  },
  "output_schema": {
    "output": {
      "type": "string"
    }
  },
  "license": "apache-2.0",
  "hardware": "2.9.4",
  "sdk": "gradio",
  "tags": [
    "gradio",
    "region:us"
  ],
  "likes": 6,
  "last_modified": "2022-05-01 06:52:01+00:00",
  "readme_excerpt": "",
  "_real_scraped": true,
  "estimated_latency_s": 10.0,
  "speed_tier": "medium",
  "_latency_source": "inferred",
  "_api_scraped": true,
  "_api_status": "error",
  "_api_error": "_ssl.c:983: The handshake operation timed out"
}