{
  "space_id": "merve/BigGAN-ImageNET",
  "title": "BigGAN ImageNET",
  "emoji": "\ud83e\udd9a",
  "description": "BigGAN ImageNET",
  "input_schema": {
    "input": {
      "type": "string",
      "description": "Input",
      "required": true
    }
  },
  "output_schema": {
    "output": {
      "type": "string"
    }
  },
  "license": "unknown",
  "hardware": "",
  "sdk": "gradio",
  "tags": [
    "gradio",
    "region:us",
    "image-generation",
    "text-to-image",
    "vision"
  ],
  "likes": 4,
  "last_modified": "2021-12-23 18:09:59+00:00",
  "readme_excerpt": "",
  "_real_scraped": true,
  "_tags_enriched": true,
  "estimated_latency_s": 30.0,
  "speed_tier": "slow",
  "_latency_source": "inferred",
  "_api_scraped": true,
  "_api_status": "error",
  "_api_error": "(Request ID: Root=1-69e77bcb-527be528064d4b495695e55b;f91b7035-6847-45bf-88cb-2f9e8e77e02c)\n\n429 Too Many Requests: you have reached your 'api' rate limit.\nRetry after 19 seconds (0/2500 requests rema"
}