{
  "space_id": "mfrashad/CharacterGAN",
  "title": "CharacterGAN",
  "emoji": "\ud83e\uddcd\u200d\u2642\ufe0f\ud83e\udddc\u200d\u2640\ufe0f\ud83d\udd74",
  "description": "CharacterGAN",
  "input_schema": {
    "input": {
      "type": "string",
      "description": "Input",
      "required": true
    }
  },
  "output_schema": {
    "output": {
      "type": "string"
    }
  },
  "license": "cc-by-nc-4.0",
  "hardware": "2.9.4",
  "sdk": "gradio",
  "tags": [
    "gradio",
    "region:us"
  ],
  "likes": 10,
  "last_modified": "2022-11-25 06:52:00+00:00",
  "readme_excerpt": "",
  "_real_scraped": true,
  "_api_scraped": true,
  "_api_status": "sleeping",
  "_api_error": "Space is in RUNTIME_ERROR state",
  "estimated_latency_s": 10.0,
  "speed_tier": "medium",
  "_latency_source": "inferred"
}