{
  "space_id": "ORI-Muchim/NahidaTTS",
  "title": "NahidaTTS",
  "emoji": "\ud83c\udf43",
  "description": "NahidaTTS",
  "input_schema": {
    "input": {
      "type": "string",
      "description": "Input",
      "required": true
    }
  },
  "output_schema": {
    "output": {
      "type": "string"
    }
  },
  "license": "mit",
  "hardware": "3.12.0",
  "sdk": "gradio",
  "tags": [
    "gradio",
    "region:us"
  ],
  "likes": 4,
  "last_modified": "2024-02-28 14:54:54+00:00",
  "readme_excerpt": "",
  "_real_scraped": true,
  "_tags_enriched": true,
  "estimated_latency_s": 4.0,
  "speed_tier": "fast",
  "_latency_source": "inferred",
  "_api_scraped": true,
  "_api_status": "error",
  "_api_error": "(Request ID: Root=1-69e77bd4-77427cba75e0f9086a19b837;ef37d3cc-7220-434d-8dcd-3283499c6477)\n\n429 Too Many Requests: you have reached your 'api' rate limit.\nRetry after 10 seconds (0/2500 requests rema"
}