{
  "space_id": "rajistics/library_metrics_forecasting",
  "title": "Library_metrics_forecasting",
  "emoji": "\ud83d\udc28",
  "description": "Library_metrics_forecasting",
  "input_schema": {
    "input": {
      "type": "string",
      "description": "Input",
      "required": true
    }
  },
  "output_schema": {
    "output": {
      "type": "string"
    }
  },
  "license": "apache-2.0",
  "hardware": "3.0.5",
  "sdk": "gradio",
  "tags": [
    "gradio",
    "region:us"
  ],
  "likes": 3,
  "last_modified": "2023-02-19 21:18:01+00:00",
  "readme_excerpt": "",
  "_real_scraped": true,
  "estimated_latency_s": 10.0,
  "speed_tier": "medium",
  "_latency_source": "inferred",
  "_api_scraped": true,
  "_api_status": "sleeping",
  "_api_error": "Space is in RUNTIME_ERROR state"
}