{
  "space_id": "raynardj/modern-chinese-to-ancient-translate-wenyanwen",
  "title": "Modern Chinese To Ancient Translate Wenyanwen",
  "emoji": "\ud83c\udf76",
  "description": "Modern Chinese To Ancient Translate Wenyanwen",
  "input_schema": {
    "input": {
      "type": "string",
      "description": "Input",
      "required": true
    }
  },
  "output_schema": {
    "output": {
      "type": "string"
    }
  },
  "license": "unknown",
  "hardware": "",
  "sdk": "streamlit",
  "tags": [
    "streamlit",
    "region:us",
    "text",
    "translation"
  ],
  "likes": 9,
  "last_modified": "2023-10-19 05:37:43+00:00",
  "readme_excerpt": "",
  "_real_scraped": true,
  "_api_scraped": true,
  "_api_status": "sleeping",
  "_api_error": "Space is in RUNTIME_ERROR state",
  "estimated_latency_s": 10.0,
  "speed_tier": "medium",
  "_latency_source": "inferred",
  "_tags_enriched": true
}