{
  "space_id": "Selfit/ImageEditPro",
  "title": "ImageEditPro",
  "emoji": "\ud83d\udc28",
  "description": "AI-powered image editing tool",
  "input_schema": {
    "input": {
      "type": "string",
      "description": "Input",
      "required": true
    }
  },
  "output_schema": {
    "output": {
      "type": "string"
    }
  },
  "license": "mit",
  "hardware": "5.44.1",
  "sdk": "gradio",
  "tags": [
    "gradio",
    "region:us"
  ],
  "likes": 661,
  "last_modified": "2025-12-21 12:02:15+00:00",
  "readme_excerpt": "",
  "_real_scraped": true,
  "_api_scraped": true,
  "_api_status": "ok",
  "endpoints": [],
  "_api_verified": true,
  "estimated_latency_s": 2.62,
  "speed_tier": "fast",
  "_latency_source": "measured",
  "measured_latency_s": 2.62,
  "measurement_method": "gradio_client_init_plus_view_api",
  "measurement_timestamp": "2026-04-20T07:49:55.483935+00:00"
}