{
  "space_id": "somosnlp-hackathon-2022/extractive-qa-biomedicine",
  "title": "Extractive Qa Biomedicine",
  "emoji": "\ud83e\udda0",
  "description": "Extractive Qa Biomedicine",
  "input_schema": {
    "input": {
      "type": "string",
      "description": "Input",
      "required": true
    }
  },
  "output_schema": {
    "output": {
      "type": "string"
    }
  },
  "license": "other",
  "hardware": "2.9.1",
  "sdk": "gradio",
  "tags": [
    "gradio",
    "region:us"
  ],
  "likes": 5,
  "last_modified": "2022-04-04 04:35:51+00:00",
  "readme_excerpt": "",
  "_real_scraped": true,
  "estimated_latency_s": 10.0,
  "speed_tier": "medium",
  "_latency_source": "inferred",
  "_api_scraped": true,
  "_api_status": "error",
  "_api_error": "(Request ID: Root=1-69e77b90-72af6568352836d31a8f375b;29e26b32-94aa-48c8-8732-8aa8bc8f8f66)\n\n429 Too Many Requests: you have reached your 'api' rate limit.\nRetry after 78 seconds (0/2500 requests rema"
}